omnip/__init__.py
omnip/chat.py
omnip-0.0.1.dist-info/LICENSE
omnip-0.0.1.dist-info/METADATA
omnip-0.0.1.dist-info/WHEEL
omnip-0.0.1.dist-info/RECORD
