Metadata-Version: 2.1
Name: omnip
Version: 0.0.1
Summary: 🚀Omnip: Omni post
Home-page: https://github.com/Undertone0809/omnip
License: MIT
Keywords: Omnip,xhs,twitter
Author: Zeeland
Author-email: zeeland4work@gmail.com
Requires-Python: >=3.8.0,<4.0
Classifier: License :: OSI Approved :: MIT License
Classifier: Programming Language :: Python :: 3
Classifier: Programming Language :: Python :: 3.8
Classifier: Programming Language :: Python :: 3.9
Classifier: Programming Language :: Python :: 3.10
Classifier: Programming Language :: Python :: 3.11
Classifier: Programming Language :: Python :: 3.12
Project-URL: Repository, https://github.com/Undertone0809/omnip
